py_gitignore_tools/__init__.py
py_gitignore_tools/templates/python.gitignore
py_gitignore_tools-0.1.4.dist-info/licenses/LICENSE
py_gitignore_tools-0.1.4.dist-info/METADATA
py_gitignore_tools-0.1.4.dist-info/WHEEL
py_gitignore_tools-0.1.4.dist-info/entry_points.txt
py_gitignore_tools-0.1.4.dist-info/top_level.txt
py_gitignore_tools-0.1.4.dist-info/RECORD
