Metadata-Version: 2.4
Name: py-gitignore-tools
Version: 0.1.4
Summary: Generador de archivos .gitignore listos para producción en proyectos Python, Django y Flask
Author: Urian Viera
License: MIT License
Project-URL: Homepage, https://urianviera.com
Project-URL: Source, https://github.com/urian121
Project-URL: YouTube, https://www.youtube.com/WebDeveloperUrianViera
Project-URL: LinkedIn, https://www.linkedin.com/in/urian-viera/
License-File: LICENSE
Dynamic: license-file
